mcore_organization_chart/__init__.py
mcore_organization_chart/api_service.py
mcore_organization_chart/cli.py
mcore_organization_chart/core.py
mcore_organization_chart/tests.py
mcore_organization_chart-1.0.0.dist-info/METADATA
mcore_organization_chart-1.0.0.dist-info/RECORD
mcore_organization_chart-1.0.0.dist-info/WHEEL
mcore_organization_chart-1.0.0.dist-info/entry_points.txt
mcore_organization_chart-1.0.0.dist-info/top_level.txt
