Metadata-Version: 2.1
Name: mcore-organization-chart
Version: 1.0.0
Summary: Migacore Technologies Technical Coding Challenge Solution
Home-page: https://github.com/spin14/mcore-organization-chart
Author: Acciaioli Valverde
Author-email: acci.valverde@gmail.com
License: MIT license
Keywords: mcore_organization_chart
Platform: UNKNOWN
Classifier: License :: OSI Approved :: MIT License
Classifier: Natural Language :: English
Classifier: Programming Language :: Python :: 3.6
Requires-Dist: Click (>=6.0)
Requires-Dist: requests
